{
  "type": "immersiveengineering:cloche",
  "input": {
    "item": "croptopia:sweetpotato_seed"
  },
  "soil": {
    "item": "minecraft:dirt"
  },
  "results": [
    {
      "id": "croptopia:sweetpotato",
      "Count": 2
    },
    {
      "id": "croptopia:sweetpotato_seed"
    }
  ],
  "time": 640,
  "render": {
    "type": "immersiveengineering:crop",
    "block": "croptopia:sweetpotato_crop"
  },
  "neoforge:conditions": [
    {
      "type": "neoforge:mod_loaded",
      "modid": "immersiveengineering"
    }
  ]
}
